setup.py
mcav/__init__.py
mcav/mca.py
mcav/mcav.py
mcav/sca.py
mcav/scav.py
mcav/zipf.py
mcav.egg-info/PKG-INFO
mcav.egg-info/SOURCES.txt
mcav.egg-info/dependency_links.txt
mcav.egg-info/top_level.txt