Metadata-Version: 1.0
Name: mcav
Version: 0.1
Summary: sca scav mca mcav
Home-page: https://github.com/kanyuanzhi/ndnSIM-data-process/tree/master/src/mcav
Author: Kan
Author-email: kanyuanzhi@gmail.com
License: MIT license
Platform: all
